simple_sagemaker/__init__.py
simple_sagemaker/cli.py
simple_sagemaker/constants.py
simple_sagemaker/ecr_sync.py
simple_sagemaker/iam_utils.py
simple_sagemaker/s3_sync.py
simple_sagemaker/shell_launcher.py
simple_sagemaker/sm_project.py
simple_sagemaker/sm_task.py
simple_sagemaker/worker_toolkit/__init__.py
simple_sagemaker/worker_toolkit/worker_lib.py
simple_sagemaker-0.9.24.dist-info/LICENSE
simple_sagemaker-0.9.24.dist-info/METADATA
simple_sagemaker-0.9.24.dist-info/WHEEL
simple_sagemaker-0.9.24.dist-info/entry_points.txt
simple_sagemaker-0.9.24.dist-info/top_level.txt
simple_sagemaker-0.9.24.dist-info/RECORD
