Metadata-Version: 2.1
Name: simple-sagemaker
Version: 0.9.24
Summary: A **simpler** and **cheaper** way to distribute work (python/shell/training) work on machines of your choice in the (AWS) cloud
Home-page: https://github.com/shiftan/simple_sagemaker
Author: Ariel Shiftan
Maintainer: Ariel Shiftan
Maintainer-email: shiftan@gmail.com
License: Apache 2.0
Project-URL: Source, https://github.com/shiftan/simple_sagemaker
Project-URL: Tracker, https://github.com/shiftan/simple_sagemaker
Keywords: sagemaker,aws
Platform: any
Classifier: Programming Language :: Python :: 3.8
Classifier: Programming Language :: Python :: 3.7
Classifier: Programming Language :: Python :: 3.6
Classifier: License :: OSI Approved :: Apache Software License
Classifier: Topic :: Software Development :: Libraries
Classifier: Topic :: Utilities
Requires-Python: >=3.6
Requires-Dist: docker
Requires-Dist: boto3
Requires-Dist: sagemaker
Provides-Extra: docs
Requires-Dist: sphinx (>=2.0.0) ; extra == 'docs'
Provides-Extra: testing
Requires-Dist: pytest (>=4.0.0) ; extra == 'testing'
